{
  "deposits": [
    {
      "title": "Вклад СОХРАНЯЙ и СОХРАНЯЙ ОнЛ@йн",
      "rateOnline": "до 3,50% в рублях — в Сбербанк Онлайн",
      "rateOffline": "до 3,35% в рублях — в отделении Банка",
      "termFrom": "от 1 месяца",
      "termTo": "до 3-х лет",
      "amountFromRUR": "от 1000 рублей",
      "amountFromUSD": ""
    },
    {
      "title": "Вклад ПОПОЛНЯЙ и ПОПОЛНЯЙ ОнЛ@йн",
      "rateOnline": "до 3,05% в рублях — в Сбербанк Онлайн",
      "rateOffline": "до 2,90% в рублях — в отделении Банка",
      "termFrom": "от 3 месяцев",
      "termTo": "до 3-х лет",
      "amountFromRUR": "от 1000 рублей",
      "amountFromUSD": ""
    }
  ],
  "disclaimer": "Узнать подробнее  \n<a href=\"http://www.sberbank.ru/ru/person/contributions/deposits/renew_online\" target=\"_blank\" rel='nofollow'>\n О вкладе Пополняй\n</a>\n  \n<a href=\"http://www.sberbank.ru/ru/person/contributions/deposits/save_online\" target=\"_blank\" rel='nofollow'>\n О вкладе Сохраняй\n</a>"
}
